smsReceiver
