Metadata-Version: 1.0
Name: smsReceiver
Version: 2.0
Summary: Module to get online number to receive SMS
Home-page: https://github.com/mthbernardes/smsReceiver
Author: Matheus Bernardes
Author-email: mthbernardes@gmail.com
License: MIT License
Keywords: sms receive
Platform: UNKNOWN
